alibabacloud_gateway_oss/__init__.py
alibabacloud_gateway_oss/client.py
alibabacloud_gateway_oss-0.0.24.dist-info/METADATA
alibabacloud_gateway_oss-0.0.24.dist-info/WHEEL
alibabacloud_gateway_oss-0.0.24.dist-info/top_level.txt
alibabacloud_gateway_oss-0.0.24.dist-info/RECORD
