Metadata-Version: 2.1
Name: alibabacloud-gateway-oss
Version: 0.0.24
Summary: Alibaba Cloud OSS SDK Library for Python
Home-page: https://github.com/aliyun/alibabacloud-gateway
Author: Alibaba Cloud SDK
Author-email: sdk-team@alibabacloud.com
License: Apache License 2.0
Keywords: alibabacloud,gateway,oss
Platform: any
Classifier: Development Status :: 4 - Beta
Classifier: Intended Audience :: Developers
Classifier: License :: OSI Approved :: Apache Software License
Classifier: Programming Language :: Python
Classifier: Programming Language :: Python :: 3
Classifier: Programming Language :: Python :: 3.6
Classifier: Programming Language :: Python :: 3.7
Classifier: Programming Language :: Python :: 3.8
Classifier: Programming Language :: Python :: 3.9
Classifier: Topic :: Software Development
Requires-Python: >=3.6
Requires-Dist: alibabacloud-credentials (>=0.3.5)
Requires-Dist: alibabacloud-darabonba-array (<1.0.0,>=0.1.0)
Requires-Dist: alibabacloud-darabonba-encode-util (<1.0.0,>=0.0.2)
Requires-Dist: alibabacloud-darabonba-map (<1.0.0,>=0.0.1)
Requires-Dist: alibabacloud-darabonba-signature-util (<1.0.0,>=0.0.4)
Requires-Dist: alibabacloud-darabonba-string (<1.0.0,>=0.0.4)
Requires-Dist: alibabacloud-darabonba-time (<1.0.0,>=0.0.1)
Requires-Dist: alibabacloud-gateway-oss-util (<1.0.0,>=0.0.10)
Requires-Dist: alibabacloud-gateway-spi (<1.0.0,>=0.0.1)
Requires-Dist: alibabacloud-openapi-util (<1.0.0,>=0.2.1)
Requires-Dist: alibabacloud-oss-util (<1.0.0,>=0.0.5)
Requires-Dist: alibabacloud-tea-util (<1.0.0,>=0.3.11)
Requires-Dist: alibabacloud-tea-xml (<1.0.0,>=0.0.2)
Requires-Dist: darabonba-core (<2.0.0,>=1.0.4)
